pyzafa/__init__.py
pyzafa/data_encoding.py
pyzafa-1.2.0.dist-info/METADATA
pyzafa-1.2.0.dist-info/WHEEL
pyzafa-1.2.0.dist-info/top_level.txt
pyzafa-1.2.0.dist-info/RECORD
