Metadata-Version: 2.1
Name: pyzafa
Version: 1.2.0
Summary: Python自用小功能
Home-page: https://github.com/taishengxin/pyzafa
Author: taishengxin
Author-email: taishengxin@gmail.com
License: MIT
Platform: UNKNOWN
Classifier: License :: OSI Approved :: MIT License
Classifier: Programming Language :: Python
Classifier: Programming Language :: Python :: 3
Classifier: Programming Language :: Python :: 3.6
Classifier: Programming Language :: Python :: Implementation :: CPython
Classifier: Programming Language :: Python :: Implementation :: PyPy
Classifier: Topic :: Scientific/Engineering :: Bio-Informatics
Requires-Python: >=3.6.0
